<?xml version="1.0" encoding="UTF-8"?>
<!DOCTYPE plist PUBLIC "-//Apple//DTD PLIST 1.0//EN" "http://www.apple.com/DTDs/PropertyList-1.0.dtd"/>

<plist version="1.0">
    <dict>
        <key>ROOT</key>
        <array>
            <dict>
                <key>id</key>
                <string>199</string>
                <key>Asset</key>
                <dict>
                    <key>value</key>
                    <string>191</string>
                </dict>
            </dict>
            <dict>
                <key>id</key>
                <string>223</string>
                <key>Asset</key>
                <dict>
                    <key>value</key>
                    <string>191</string>
                </dict>
            </dict>
            <dict>
                <key>id</key>
                <string>1740</string>
                <key>Asset</key>
                <dict>
                    <key>value</key>
                    <string>191</string>
                </dict>
            </dict>
            <dict>
                <key>id</key>
                <string>1823</string>
                <key>Asset</key>
                <dict>
                    <key>value</key>
                    <string>191</string>
                </dict>
            </dict>
            <dict>
                <key>id</key>
                <string>1921</string>
                <key>Asset</key>
                <dict>
                    <key>value</key>
                    <string>191</string>
                </dict>
            </dict>
            <dict>
                <key>id</key>
                <string>1969</string>
                <key>Asset</key>
                <dict>
                    <key>value</key>
                    <string>191</string>
                </dict>
            </dict>
            <dict>
                <key>id</key>
                <string>2025</string>
                <key>Asset</key>
                <dict>
                    <key>value</key>
                    <string>191</string>
                </dict>
            </dict>
            <dict>
                <key>id</key>
                <string>2057</string>
                <key>Asset</key>
                <dict>
                    <key>value</key>
                    <string>191</string>
                </dict>
            </dict>
            <dict>
                <key>id</key>
                <string>2089</string>
                <key>Asset</key>
                <dict>
                    <key>value</key>
                    <string>191</string>
                </dict>
            </dict>
            <dict>
                <key>id</key>
                <string>2153</string>
                <key>Asset</key>
                <dict>
                    <key>value</key>
                    <string>191</string>
                </dict>
            </dict>
            <dict>
                <key>id</key>
                <string>2201</string>
                <key>Asset</key>
                <dict>
                    <key>value</key>
                    <string>191</string>
                </dict>
            </dict>
        </array>
    </dict>
</plist>
